Mytopsis/__init__.py
Mytopsis/topsis.py
topsis_sunvir-0.0.1.dist-info/LICENSE.lic
topsis_sunvir-0.0.1.dist-info/METADATA
topsis_sunvir-0.0.1.dist-info/WHEEL
topsis_sunvir-0.0.1.dist-info/top_level.txt
topsis_sunvir-0.0.1.dist-info/RECORD
