Metadata-Version: 2.1
Name: topsis-sunvir
Version: 0.0.1
Summary: python package to implement TOPSIS
Home-page: https://github.com/sunvir72/Topsis
Author: Sunvir Singh
Author-email: sunvirsingh72@gmail.com
License: UNKNOWN
Platform: UNKNOWN
Classifier: Programming Language :: Python :: 3
Classifier: License :: OSI Approved :: MIT License
Classifier: Operating System :: OS Independent
Requires-Python: >=3.6
